udata_youckan.py
udata_youckan-1.0.0.dist-info/DESCRIPTION.rst
udata_youckan-1.0.0.dist-info/METADATA
udata_youckan-1.0.0.dist-info/RECORD
udata_youckan-1.0.0.dist-info/WHEEL
udata_youckan-1.0.0.dist-info/metadata.json
udata_youckan-1.0.0.dist-info/top_level.txt
