Metadata-Version: 2.0
Name: udata-youckan
Version: 1.0.0
Summary: YouCKAN auth for uData
Home-page: https://github.com/etalab/udata-youckan
Author: Opendata Team
Author-email: opendatateam@data.gouv.fr
License: AGPL
Keywords: u,d,a,t,a, ,y,o,u,c,k,a,n, ,s,s,o, ,p,l,u,g,i,n
Platform: UNKNOWN
Classifier: Development Status :: 3 - Alpha
Classifier: Programming Language :: Python
Classifier: Environment :: Web Environment
Classifier: Operating System :: OS Independent
Classifier: Intended Audience :: Developers
Classifier: Topic :: System :: Software Distribution
Classifier: Programming Language :: Python
Classifier: Programming Language :: Python :: 2
Classifier: Programming Language :: Python :: 2.7
Classifier: Topic :: Software Development :: Libraries :: Python Modules
Classifier: License :: OSI Approved :: GNU Affero General Public License v3 or later (AGPLv3+)
Requires-Dist: udata
